lottie/__init__.py
lottie/nvector.py
lottie/version.py
lottie/exporters/__init__.py
lottie/exporters/base.py
lottie/exporters/cairo.py
lottie/exporters/core.py
lottie/exporters/dot_lottie.py
lottie/exporters/gif.py
lottie/exporters/pretty_print.py
lottie/exporters/sif.py
lottie/exporters/svg.py
lottie/exporters/tgs_validator.py
lottie/exporters/video.py
lottie/gui/__init__.py
lottie/gui/console.py
lottie/gui/import_export.py
lottie/gui/search_widget.py
lottie/gui/timeline_widget.py
lottie/gui/tree_view.py
lottie/importers/__init__.py
lottie/importers/aep.py
lottie/importers/base.py
lottie/importers/core.py
lottie/importers/dot_lottie.py
lottie/importers/krita.py
lottie/importers/raster.py
lottie/importers/script.py
lottie/importers/sif.py
lottie/importers/svg.py
lottie/objects/__init__.py
lottie/objects/animation.py
lottie/objects/assets.py
lottie/objects/base.py
lottie/objects/bezier.py
lottie/objects/composition.py
lottie/objects/easing.py
lottie/objects/effects.py
lottie/objects/enums.py
lottie/objects/helpers.py
lottie/objects/layers.py
lottie/objects/properties.py
lottie/objects/shapes.py
lottie/objects/styles.py
lottie/objects/text.py
lottie/parsers/__init__.py
lottie/parsers/baseporter.py
lottie/parsers/glaxnimate_helpers.py
lottie/parsers/pixel.py
lottie/parsers/raster.py
lottie/parsers/tgs.py
lottie/parsers/aep/aep_riff.py
lottie/parsers/aep/aepx.py
lottie/parsers/aep/converter.py
lottie/parsers/aep/cos.py
lottie/parsers/aep/expressions.py
lottie/parsers/aep/gradient_xml.py
lottie/parsers/aep/riff.py
lottie/parsers/sif/__init__.py
lottie/parsers/sif/api.py
lottie/parsers/sif/ast.py
lottie/parsers/sif/builder.py
lottie/parsers/sif/converter.py
lottie/parsers/sif/importer.py
lottie/parsers/sif/ast_impl/__init__.py
lottie/parsers/sif/ast_impl/base.py
lottie/parsers/sif/ast_impl/nodes.py
lottie/parsers/sif/sif/__init__.py
lottie/parsers/sif/sif/core.py
lottie/parsers/sif/sif/enums.py
lottie/parsers/sif/sif/frame_time.py
lottie/parsers/sif/sif/nodes.py
lottie_ps-0.7.2.dist-info/COPYING
lottie_ps-0.7.2.dist-info/METADATA
lottie_ps-0.7.2.dist-info/WHEEL
lottie_ps-0.7.2.dist-info/top_level.txt
lottie_ps-0.7.2.dist-info/zip-safe
lottie_ps-0.7.2.dist-info/RECORD
