Metadata-Version: 2.1
Name: lottie-ps
Version: 0.7.2
Summary: A framework to work with lottie files and telegram animated stickers (tgs)
Home-page: https://gitlab.com/mattbas/python-lottie/
Author: Mattia Basaglia
Author-email: mattia.basaglia@gmail.com
License: GNU Affero General Public License v3 or later (AGPLv3+)
Project-URL: Code, https://gitlab.com/mattbas/python-lottie/
Project-URL: Documentation, https://mattbas.gitlab.io/python-lottie/index.html
Project-URL: Chat, https://t.me/tgs_stuff
Project-URL: Coverage, https://mattbas.gitlab.io/python-lottie/coverage/
Project-URL: Downloads, https://mattbas.gitlab.io/python-lottie/downloads.html
Keywords: telegram stickers tgs lottie svg animation
Classifier: Programming Language :: Python :: 3
Classifier: Development Status :: 4 - Beta
Classifier: License :: OSI Approved :: GNU Affero General Public License v3 or later (AGPLv3+)
Classifier: Operating System :: OS Independent
Classifier: Topic :: Multimedia :: Graphics
Requires-Python: >=3
License-File: COPYING
Provides-Extra: aep
Requires-Dist: pillow ; extra == 'aep'
Requires-Dist: esprima ; extra == 'aep'
Requires-Dist: escodegen ; extra == 'aep'
Provides-Extra: animatedsvg
Requires-Dist: glaxnimate ; extra == 'animatedsvg'
Provides-Extra: gif
Requires-Dist: glaxnimate ; extra == 'gif'
Requires-Dist: pillow ; extra == 'gif'
Provides-Extra: gui
Requires-Dist: QScintilla ; extra == 'gui'
Provides-Extra: pdf
Requires-Dist: cairosvg ; extra == 'pdf'
Provides-Extra: png
Requires-Dist: glaxnimate ; extra == 'png'
Provides-Extra: all
Requires-Dist: opencv-python ; extra == 'all'
Requires-Dist: escodegen ; extra == 'all'
Requires-Dist: glaxnimate ; extra == 'all'
Requires-Dist: pillow ; extra == 'all'
Requires-Dist: QScintilla ; extra == 'all'
Requires-Dist: esprima ; extra == 'all'
Requires-Dist: cairosvg ; extra == 'all'
Requires-Dist: numpy ; extra == 'all'
Requires-Dist: grapheme ; extra == 'all'
Requires-Dist: fonttools ; extra == 'all'
Provides-Extra: emoji
Requires-Dist: grapheme ; extra == 'emoji'
Provides-Extra: images
Requires-Dist: pillow ; extra == 'images'
Provides-Extra: text
Requires-Dist: fonttools ; extra == 'text'
Provides-Extra: trace
Requires-Dist: glaxnimate ; extra == 'trace'
Requires-Dist: pillow ; extra == 'trace'
Provides-Extra: video
Requires-Dist: opencv-python ; extra == 'video'
Requires-Dist: pillow ; extra == 'video'
Requires-Dist: numpy ; extra == 'video'
